{
  "project_info": {
    "project_number": "608445591766",
    "firebase_url": "https://homebank-1dbee.firebaseio.com",
    "project_id": "homebank-1dbee",
    "storage_bucket": "homebank-1dbee.appspot.com"
  },
  "client": [
    {
      "client_info": {
        "mobilesdk_app_id": "1:608445591766:android:8389790e91b523ce",
        "android_client_info": {
          "package_name": "kz.batana.homecreditloyalty"
        }
      },
      "oauth_client": [
        {
          "client_id": "608445591766-2d2a7gtlumahajl6grphqt35sner849c.apps.googleusercontent.com",
          "client_type": 3
        }
      ],
      "api_key": [
        {
          "current_key": "AIzaSyDws5zUEGEIJtBAxJjHGa5jnelU9knLqf8"
        }
      ],
      "services": {
        "analytics_service": {
          "status": 1
        },
        "appinvite_service": {
          "status": 1,
          "other_platform_oauth_client": []
        },
        "ads_service": {
          "status": 2
        }
      }
    }
  ],
  "configuration_version": "1"
}